{
  "api_predictions_2025-08-19": [
    {
      "timestamp": "2025-08-21T09:33:30.461786",
      "function": "api_predictions_2025-08-19",
      "execution_time": 0.001,
      "success": true,
      "error": null
    },
    {
      "timestamp": "2025-08-21T09:36:19.714621",
      "function": "api_predictions_2025-08-19",
      "execution_time": 0.0,
      "success": true,
      "error": null
    },
    {
      "timestamp": "2025-08-21T09:38:35.557839",
      "function": "api_predictions_2025-08-19",
      "execution_time": 0.0,
      "success": true,
      "error": null
    },
    {
      "timestamp": "2025-08-21T09:41:24.866856",
      "function": "api_predictions_2025-08-19",
      "execution_time": 0.004,
      "success": true,
      "error": null
    },
    {
      "timestamp": "2025-08-21T09:43:40.715363",
      "function": "api_predictions_2025-08-19",
      "execution_time": 0.0,
      "success": true,
      "error": null
    }
  ]
}