{
  "date": "2025-08-25",
  "generated_at": "2025-08-25T09:50:08.595299",
  "source": "Unified Betting Engine v1.0",
  "games": {
    "Boston Red Sox_vs_Baltimore Orioles": {
      "away_team": "Boston Red Sox",
      "home_team": "Baltimore Orioles",
      "away_pitcher": null,
      "home_pitcher": null,
      "predicted_score": "3.4-3.6",
      "predicted_total_runs": 7.0,
      "win_probabilities": {
        "away_prob": 0.478,
        "home_prob": 0.522
      },
      "value_bets": [
        {
          "type": "total",
          "recommendation": "Under 9.5",
          "expected_value": 0.40217391304347827,
          "win_probability": 0.75,
          "american_odds": "-115",
          "confidence": "high",
          "predicted_total": 7.0,
          "betting_line": 9.5,
          "reasoning": "Predicted 7.0 vs line 9.5"
        }
      ]
    },
    "Tampa Bay Rays_vs_Cleveland Guardians": {
      "away_team": "Tampa Bay Rays",
      "home_team": "Cleveland Guardians",
      "away_pitcher": null,
      "home_pitcher": null,
      "predicted_score": "5.5-6.0",
      "predicted_total_runs": 11.5,
      "win_probabilities": {
        "away_prob": 0.44,
        "home_prob": 0.56
      },
      "value_bets": [
        {
          "type": "total",
          "recommendation": "Over 7.5",
          "expected_value": 0.7653846153846154,
          "win_probability": 0.9,
          "american_odds": "-104",
          "confidence": "high",
          "predicted_total": 11.5,
          "betting_line": 7.5,
          "reasoning": "Predicted 11.5 vs line 7.5"
        },
        {
          "type": "moneyline",
          "recommendation": "Cleveland Guardians ML",
          "expected_value": 0.15360000000000018,
          "win_probability": 0.56,
          "american_odds": "106",
          "confidence": "low",
          "reasoning": "Model projects 56.0% win probability vs 48.5% implied odds"
        }
      ]
    },
    "Atlanta Braves_vs_Miami Marlins": {
      "away_team": "Atlanta Braves",
      "home_team": "Miami Marlins",
      "away_pitcher": null,
      "home_pitcher": null,
      "predicted_score": "3.5-3.7",
      "predicted_total_runs": 7.2,
      "win_probabilities": {
        "away_prob": 0.487,
        "home_prob": 0.513
      },
      "value_bets": []
    },
    "Washington Nationals_vs_New York Yankees": {
      "away_team": "Washington Nationals",
      "home_team": "New York Yankees",
      "away_pitcher": null,
      "home_pitcher": null,
      "predicted_score": "4.4-4.7",
      "predicted_total_runs": 9.1,
      "win_probabilities": {
        "away_prob": 0.464,
        "home_prob": 0.536
      },
      "value_bets": []
    },
    "Minnesota Twins_vs_Toronto Blue Jays": {
      "away_team": "Minnesota Twins",
      "home_team": "Toronto Blue Jays",
      "away_pitcher": null,
      "home_pitcher": null,
      "predicted_score": "3.4-3.7",
      "predicted_total_runs": 7.1,
      "win_probabilities": {
        "away_prob": 0.46,
        "home_prob": 0.54
      },
      "value_bets": []
    },
    "Philadelphia Phillies_vs_New York Mets": {
      "away_team": "Philadelphia Phillies",
      "home_team": "New York Mets",
      "away_pitcher": null,
      "home_pitcher": null,
      "predicted_score": "4.3-4.5",
      "predicted_total_runs": 8.8,
      "win_probabilities": {
        "away_prob": 0.468,
        "home_prob": 0.532
      },
      "value_bets": [
        {
          "type": "total",
          "recommendation": "Over 8.0",
          "expected_value": 0.1716000000000002,
          "win_probability": 0.5800000000000001,
          "american_odds": "102",
          "confidence": "low",
          "predicted_total": 8.8,
          "betting_line": 8.0,
          "reasoning": "Predicted 8.8 vs line 8.0"
        }
      ]
    },
    "Kansas City Royals_vs_Chicago White Sox": {
      "away_team": "Kansas City Royals",
      "home_team": "Chicago White Sox",
      "away_pitcher": null,
      "home_pitcher": null,
      "predicted_score": "5.7-5.8",
      "predicted_total_runs": 11.5,
      "win_probabilities": {
        "away_prob": 0.481,
        "home_prob": 0.519
      },
      "value_bets": [
        {
          "type": "total",
          "recommendation": "Over 8.5",
          "expected_value": 0.6160000000000001,
          "win_probability": 0.8,
          "american_odds": "102",
          "confidence": "high",
          "predicted_total": 11.5,
          "betting_line": 8.5,
          "reasoning": "Predicted 11.5 vs line 8.5"
        }
      ]
    },
    "Arizona Diamondbacks_vs_Milwaukee Brewers": {
      "away_team": "Arizona Diamondbacks",
      "home_team": "Milwaukee Brewers",
      "away_pitcher": null,
      "home_pitcher": null,
      "predicted_score": "3.4-3.7",
      "predicted_total_runs": 7.2,
      "win_probabilities": {
        "away_prob": 0.44,
        "home_prob": 0.56
      },
      "value_bets": [
        {
          "type": "total",
          "recommendation": "Under 8.0",
          "expected_value": 0.10727272727272719,
          "win_probability": 0.58,
          "american_odds": "-110",
          "confidence": "low",
          "predicted_total": 7.2,
          "betting_line": 8.0,
          "reasoning": "Predicted 7.2 vs line 8.0"
        }
      ]
    },
    "Pittsburgh Pirates_vs_St. Louis Cardinals": {
      "away_team": "Pittsburgh Pirates",
      "home_team": "St. Louis Cardinals",
      "away_pitcher": null,
      "home_pitcher": null,
      "predicted_score": "3.7-4.1",
      "predicted_total_runs": 7.9,
      "win_probabilities": {
        "away_prob": 0.451,
        "home_prob": 0.549
      },
      "value_bets": []
    },
    "Los Angeles Angels_vs_Texas Rangers": {
      "away_team": "Los Angeles Angels",
      "home_team": "Texas Rangers",
      "away_pitcher": null,
      "home_pitcher": null,
      "predicted_score": "5.5-5.9",
      "predicted_total_runs": 11.4,
      "win_probabilities": {
        "away_prob": 0.457,
        "home_prob": 0.543
      },
      "value_bets": [
        {
          "type": "total",
          "recommendation": "Over 7.5",
          "expected_value": 0.7711881188118814,
          "win_probability": 0.8900000000000001,
          "american_odds": "-101",
          "confidence": "high",
          "predicted_total": 11.4,
          "betting_line": 7.5,
          "reasoning": "Predicted 11.4 vs line 7.5"
        }
      ]
    },
    "San Diego Padres_vs_Seattle Mariners": {
      "away_team": "San Diego Padres",
      "home_team": "Seattle Mariners",
      "away_pitcher": null,
      "home_pitcher": null,
      "predicted_score": "5.1-5.4",
      "predicted_total_runs": 10.5,
      "win_probabilities": {
        "away_prob": 0.463,
        "home_prob": 0.537
      },
      "value_bets": [
        {
          "type": "total",
          "recommendation": "Over 8.0",
          "expected_value": 0.40217391304347827,
          "win_probability": 0.75,
          "american_odds": "-115",
          "confidence": "high",
          "predicted_total": 10.5,
          "betting_line": 8.0,
          "reasoning": "Predicted 10.5 vs line 8.0"
        }
      ]
    },
    "Detroit Tigers_vs_Athletics": {
      "away_team": "Detroit Tigers",
      "home_team": "Athletics",
      "away_pitcher": null,
      "home_pitcher": null,
      "predicted_score": "3.5-3.6",
      "predicted_total_runs": 7.1,
      "win_probabilities": {
        "away_prob": 0.485,
        "home_prob": 0.515
      },
      "value_bets": []
    },
    "Cincinnati Reds_vs_Los Angeles Dodgers": {
      "away_team": "Cincinnati Reds",
      "home_team": "Los Angeles Dodgers",
      "away_pitcher": null,
      "home_pitcher": null,
      "predicted_score": "4.1-4.4",
      "predicted_total_runs": 8.5,
      "win_probabilities": {
        "away_prob": 0.463,
        "home_prob": 0.537
      },
      "value_bets": []
    }
  },
  "summary": {
    "total_games_analyzed": 13,
    "games_with_betting_lines": 0,
    "total_value_bets": 8,
    "high_confidence_bets": 5,
    "medium_confidence_bets": 0
  }
}